{
  "alias": "2scale.akvoflow.org",
  "app": "akvoflow-198",
  "defaultLanguageCode": "en",
  "name": "BSS",
  "questionGroup": [
    {
      "heading": "Business Support Service (BSS) Details",
      "question": [
        {
          "cascadeResource": "cascade-30100013-v73.sqlite",
          "help": { "text": null },
          "id": "4100002",
          "levels": {
            "level": [
              { "text": "Country Name" },
              { "text": "Partnership Code" }
            ]
          },
          "localeNameFlag": true,
          "mandatory": true,
          "order": "1",
          "text": "Partnership for which  the BSS support",
          "type": "cascade"
        },
        {
          "id": "28150003",
          "localeNameFlag": true,
          "mandatory": true,
          "order": "2",
          "text": "Name of the BSS",
          "type": "free"
        },
        {
          "id": "20160004",
          "localeNameFlag": false,
          "mandatory": true,
          "order": "3",
          "text": "Name of contact person: (FAMILY NAME_First name)",
          "type": "free"
        },
        {
          "id": "10130006",
          "localeNameFlag": false,
          "mandatory": true,
          "order": "4",
          "text": "Job title of contact person (Example CEO, Manager etc)",
          "type": "free"
        },
        {
          "id": "14180004",
          "localeNameFlag": false,
          "mandatory": true,
          "options": {
            "allowMultiple": false,
            "allowOther": false,
            "option": [
              { "text": "Male", "value": "Male" },
              { "text": "Female", "value": "Female" }
            ],
            "renderType": "radio"
          },
          "order": "5",
          "text": "Sex of contact person (Male/Female)",
          "type": "option"
        },
        {
          "id": "22570004",
          "localeNameFlag": false,
          "mandatory": true,
          "options": {
            "allowMultiple": false,
            "allowOther": false,
            "option": [
              { "text": "Equal/Below 35yrs", "value": "Equal/Below 35yrs" },
              { "text": "Above 35yrs", "value": "Above 35yrs" }
            ],
            "renderType": "radio"
          },
          "order": "6",
          "text": "Age of contact person (under/equal 35, over 35)",
          "type": "option"
        },
        {
          "id": "34110002",
          "localeNameFlag": false,
          "mandatory": false,
          "order": "7",
          "text": "E-mail address of contact person (Example: John.Smith@gmail.com)",
          "type": "free"
        },
        {
          "id": "26200002",
          "localeNameFlag": false,
          "mandatory": false,
          "order": "8",
          "text": "Phone number of BSS contact person (Example: 0790711486)",
          "type": "free",
          "validationRule": {
            "allowDecimal": false,
            "signed": false,
            "validationType": "numeric"
          }
        },
        {
          "id": "8120003",
          "localeNameFlag": false,
          "mandatory": true,
          "order": "9",
          "text": "Date of business registration",
          "type": "date"
        },
        {
          "id": "22580002",
          "localeNameFlag": false,
          "mandatory": true,
          "order": "10",
          "text": "Start date of BSS in the partnership",
          "type": "date"
        },
        {
          "id": "32650001",
          "localeNameFlag": false,
          "mandatory": true,
          "order": "11",
          "text": "What type is the BSS? (Example: University, Private Consultant,Public Institution, SME etc)",
          "type": "free"
        },
        {
          "help": { "text": null },
          "id": "38130005",
          "localeNameFlag": false,
          "mandatory": true,
          "options": {
            "allowMultiple": true,
            "allowOther": true,
            "option": [
              { "text": "Market Research", "value": "Market Research" },
              { "text": "Capacity Building", "value": "Capacity Building" },
              {
                "text": "Community Development",
                "value": "Community Development"
              },
              {
                "text": "Monitoring and Evaluations",
                "value": "Monitoring and Evaluations"
              },
              {
                "text": "Agribusiness Support Services",
                "value": "Agribusiness Support Services"
              }
            ]
          },
          "order": "12",
          "text": "What is the main domain or specialty of the BSS? (Example: market research, capacity building)",
          "type": "option"
        }
      ],
      "repeatable": false
    },
    {
      "heading": "Business Support Service (BSS) Coach Details",
      "question": [
        {
          "id": "6120004",
          "localeNameFlag": false,
          "mandatory": false,
          "order": "1",
          "text": "Name of the coach of the BSS (FAMILY NAME_First name)",
          "type": "free"
        },
        {
          "id": "34110003",
          "localeNameFlag": false,
          "mandatory": false,
          "options": {
            "allowMultiple": false,
            "allowOther": false,
            "option": [
              { "text": "Male", "value": "Male" },
              { "text": "Female", "value": "Female" }
            ],
            "renderType": "radio"
          },
          "order": "2",
          "text": "Sex of the coach (Female/Male)",
          "type": "option"
        },
        {
          "id": "20760005",
          "localeNameFlag": false,
          "mandatory": true,
          "options": {
            "allowMultiple": false,
            "allowOther": false,
            "option": [
              { "text": "Equal/below 35yrs", "value": "Equal/below 35yrs" },
              { "text": "Above 35yrs", "value": "Above 35yrs" }
            ],
            "renderType": "radio"
          },
          "order": "3",
          "text": "Age of the coach (under/equal 35, over 35)",
          "type": "option"
        },
        {
          "help": { "text": null },
          "id": "30170002",
          "localeNameFlag": false,
          "mandatory": false,
          "order": "4",
          "text": "Phone number of the coach (Example: 0790711486)",
          "type": "free",
          "validationRule": {
            "allowDecimal": false,
            "signed": false,
            "validationType": "numeric"
          }
        },
        {
          "id": "8120004",
          "localeNameFlag": false,
          "mandatory": false,
          "order": "5",
          "text": "E-mail address of the coach (Example: John.Smith@gmail.com)",
          "type": "free"
        }
      ],
      "repeatable": true
    }
  ],
  "surveyGroupId": "32110004",
  "surveyGroupName": "Business Support Service Form",
  "surveyId": "4100001",
  "version": "46.0"
}
